openmm/lib/libOpenMMTorch.so
openmm/lib/plugins/libOpenMMTorchCUDA.so
openmm/lib/plugins/libOpenMMTorchOpenCL.so
openmm/lib/plugins/libOpenMMTorchReference.so
openmmtorch/TorchPluginWrapper.cpp
openmmtorch/__init__.py
openmmtorch/_openmmtorch.cpython-312-x86_64-linux-gnu.so
openmmtorch/openmmtorch.py
openmmtorch/include/TorchForce.h
openmmtorch/include/TorchKernels.h
openmmtorch/include/internal/TorchForceImpl.h
openmmtorch/include/internal/windowsExportTorch.h
openmm_torch_unofficial_cu11-1.5.dist-info/METADATA
openmm_torch_unofficial_cu11-1.5.dist-info/WHEEL
openmm_torch_unofficial_cu11-1.5.dist-info/top_level.txt
openmm_torch_unofficial_cu11-1.5.dist-info/RECORD
